datus_mysql/__init__.py
datus_mysql/config.py
datus_mysql/connector.py
datus_mysql-0.1.3.dist-info/METADATA
datus_mysql-0.1.3.dist-info/WHEEL
datus_mysql-0.1.3.dist-info/entry_points.txt
datus_mysql-0.1.3.dist-info/RECORD
