Metadata-Version: 2.4
Name: datus-mysql
Version: 0.1.3
Summary: MySQL database adapter for Datus
Project-URL: Homepage, https://github.com/Datus-ai/datus-db-adapters
Project-URL: Repository, https://github.com/Datus-ai/datus-db-adapters
Project-URL: Issues, https://github.com/Datus-ai/datus-db-adapters/issues
Author-email: DatusAI <support@datus.ai>
License: Apache-2.0
Keywords: adapter,database,datus,mysql
Classifier: Development Status :: 4 - Beta
Classifier: Intended Audience :: Developers
Classifier: License :: OSI Approved :: Apache Software License
Classifier: Programming Language :: Python :: 3
Classifier: Programming Language :: Python :: 3.12
Requires-Python: >=3.12
Requires-Dist: cryptography>=41.0.0
Requires-Dist: datus-agent>0.2.1
Requires-Dist: datus-sqlalchemy>=0.1.2
Requires-Dist: pydantic>=2.0.0
Requires-Dist: pymysql>=1.1.1
